{
  "upcomingEvents": [
    {
      "name": "Hack The Northeast Hackathon",
      "link": "https://www.hackthenortheast.com/",
      "time": 1642226400,
      "pastDue": false,
      "notPastDue": true,
      "desc": "Hackathon with workshops and prizes.",
      "tentative": true
    }
  ],
  "deadlines": [
    {
      "name": "Fill Out Registration Form",
      "link": "https://docs.google.com/forms/d/e/1FAIpQLSf9bBhjK4qrUeaye6wQaPgaDY0_CZc7kVo5M5DOfr1SB7RMGw/viewform",
      "hard": false,
      "time": 1600372800
    }
  ]
}
